sneakysnek
