Metadata-Version: 1.1
Name: sneakysnek
Version: 0.1.1
Summary: Dead simple cross-platform keyboard & mouse global input capture solution for Python 3.6+
Home-page: https://github.com/SerpentAI/sneakysnek
Author: Nicholas Brochu
Author-email: nicholas@serpent.ai
License: MIT
Platform: UNKNOWN
Classifier: Development Status :: 5 - Production/Stable
Classifier: Intended Audience :: Developers
Classifier: Natural Language :: English
Classifier: License :: OSI Approved :: MIT License
Classifier: Operating System :: OS Independent
Classifier: Programming Language :: Python
Classifier: Programming Language :: Python :: 3.6
